{
  "requested_url": "https://www.kdic.or.kr/sp/dpstrprot/selectProtSystBamtGiveTrgtFnst.do",
  "final_url": "https://www.kdic.or.kr/sp/dpstrprot/selectProtSystBamtGiveTrgtFnst.do",
  "status_code": 200,
  "ok": true,
  "content_type": "text/html; charset=UTF-8",
  "encoding": "UTF-8",
  "elapsed_seconds": 2.495,
  "collected_at": "2026-07-16T11:33:27+09:00",
  "content_length": 502871,
  "raw_sha256": "69a6fa918acf18449c3701cfd3ce36fada6b5bd5a7b7fb3932396fc6f48d2251",
  "redirect_history": [],
  "selected_headers": {
    "Content-Type": "text/html; charset=UTF-8",
    "Robots-Check": "unavailable:UnicodeDecodeError"
  },
  "url_id": "BI-004",
  "business_function": "예금보험금 안내",
  "page_title_manifest": "예금보험금 안내 > 보험금 지급대상 금융회사",
  "fetch_strategy": "paginated_public",
  "parser_profile": "kdic_final_media_attachment_v3",
  "raw_html_path": "raw/html/예금보험금 안내/BI-004.html"
}